ausleihe/__init__.py
ausleihe/admin.py
ausleihe/apps.py
ausleihe/forms.py
ausleihe/parsers.py
ausleihe/urls.py
ausleihe/views.py
ausleihe/migrations/0001_initial.py
ausleihe/migrations/0002_leihe.py
ausleihe/migrations/0003_alter_orderings.py
ausleihe/migrations/0004_alter_leihe_zurueckgebracht.py
ausleihe/migrations/0005_skillset_skillsetitem_skillsetitemrelation.py
ausleihe/migrations/0006_skillset_medium.py
ausleihe/migrations/0007_skill.py
ausleihe/migrations/0008_auto_20241019_1244.py
ausleihe/migrations/0009_remove_skillset_beschreibung.py
ausleihe/migrations/0010_skill_beschreibung.py
ausleihe/migrations/0011_alter_skillset_skill.py
ausleihe/migrations/0012_auto_20241021_1204.py
ausleihe/migrations/0013_auto_20241021_1206.py
ausleihe/migrations/0014_alter_skill_raeume.py
ausleihe/migrations/0015_auto_20241022_1248.py
ausleihe/migrations/0016_alter_gebaeude_lsf_id.py
ausleihe/migrations/0017_auto_20241022_1638.py
ausleihe/migrations/0018_verfuegbarkeit.py
ausleihe/migrations/0019_various_delete_changes.py
ausleihe/migrations/0020_reservierung.py
ausleihe/migrations/0021_alter_reservierung_options.py
ausleihe/migrations/0022_leihe_anfang_ende.py
ausleihe/migrations/0023_reservierung_leihe.py
ausleihe/migrations/0024_nutzungsordnung.py
ausleihe/migrations/0025_skill_anleitung.py
ausleihe/migrations/0026_skill_ist_sichtbar.py
ausleihe/migrations/0027_alter_skill_beschreibung.py
ausleihe/migrations/__init__.py
ausleihe/models/Autor.py
ausleihe/models/Buch.py
ausleihe/models/Gebaeude.py
ausleihe/models/Leihe.py
ausleihe/models/Medium.py
ausleihe/models/Nutzungsordnung.py
ausleihe/models/Raum.py
ausleihe/models/Reservierung.py
ausleihe/models/Skill.py
ausleihe/models/Skillset.py
ausleihe/models/SkillsetItem.py
ausleihe/models/SkillsetItemRelation.py
ausleihe/models/Verfuegbarkeit.py
ausleihe/models/Verlag.py
ausleihe/models/__init__.py
ausleihe/static/ausleihe/js/enter_next.js
ausleihe/static/ausleihe/js/helpers.js
ausleihe/static/ausleihe/js/skillset_edit.js
django_ausleihe-0.4.16.dist-info/LICENSE
django_ausleihe-0.4.16.dist-info/METADATA
django_ausleihe-0.4.16.dist-info/WHEEL
django_ausleihe-0.4.16.dist-info/top_level.txt
django_ausleihe-0.4.16.dist-info/RECORD
