Metadata-Version: 2.2
Name: django-ausleihe
Version: 0.4.16
Summary: Django-App für die Ausleihe von Medien.
Author-email: Martin Darmüntzel <martin@trivialanalog.de>
License: MIT
Project-URL: Homepage, https://github.com/hutchison/django-ausleihe
Project-URL: Issues, https://github.com/hutchison/django-ausleihe/issues
Classifier: Environment :: Web Environment
Classifier: Framework :: Django
Classifier: Framework :: Django :: 3.0
Classifier: Intended Audience :: Developers
Classifier: License :: OSI Approved :: MIT License
Classifier: Operating System :: OS Independent
Classifier: Programming Language :: Python
Classifier: Programming Language :: Python :: 3.9
Classifier: Topic :: Internet :: WWW/HTTP
Classifier: Topic :: Internet :: WWW/HTTP :: Dynamic Content
Requires-Python: >=3.9
License-File: LICENSE
Requires-Dist: Django>=3.1
Requires-Dist: django-fsmedhro-core>=0.3.1
Requires-Dist: djangorestframework
Requires-Dist: qrcode
Requires-Dist: markdown
